ColorTransferLib/ColorTransfer.py
ColorTransferLib/__init__.py
ColorTransferLib/Algorithms/__init__.py
ColorTransferLib/Algorithms/Afifi21/Afifi21.py
ColorTransferLib/Algorithms/Afifi21/__init__.py
ColorTransferLib/Algorithms/Afifi21/third_party/__init__.py
ColorTransferLib/Algorithms/Afifi21/third_party/color_aware_st.py
ColorTransferLib/Algorithms/Afifi21_2/Afifi21_2.py
ColorTransferLib/Algorithms/Afifi21_2/__init__.py
ColorTransferLib/Algorithms/Afifi21_2/third_party/__init__.py
ColorTransferLib/Algorithms/Afifi21_2/third_party/histoGAN.py
ColorTransferLib/Algorithms/Afifi21_2/third_party/projection_gaussian.py
ColorTransferLib/Algorithms/Afifi21_2/third_party/projection_to_latent.py
ColorTransferLib/Algorithms/Afifi21_2/third_party/rehistoGAN.py
ColorTransferLib/Algorithms/Afifi21_2/third_party/ReHistoGAN/__init__.py
ColorTransferLib/Algorithms/Afifi21_2/third_party/ReHistoGAN/rehistoGAN.py
ColorTransferLib/Algorithms/Afifi21_2/third_party/histoGAN/__init__.py
ColorTransferLib/Algorithms/Afifi21_2/third_party/histoGAN/histoGAN.py
ColorTransferLib/Algorithms/Afifi21_2/third_party/histogram_classes/LabHistBlock.py
ColorTransferLib/Algorithms/Afifi21_2/third_party/histogram_classes/RGBuvHistBlock.py
ColorTransferLib/Algorithms/Afifi21_2/third_party/histogram_classes/__init__.py
ColorTransferLib/Algorithms/Afifi21_2/third_party/histogram_classes/rgChromaHistBlock.py
ColorTransferLib/Algorithms/Afifi21_2/third_party/utils/__init__.py
ColorTransferLib/Algorithms/Afifi21_2/third_party/utils/color_transfer_MKL.py
ColorTransferLib/Algorithms/Afifi21_2/third_party/utils/diff_augment.py
ColorTransferLib/Algorithms/Afifi21_2/third_party/utils/face_preprocessing.py
ColorTransferLib/Algorithms/Afifi21_2/third_party/utils/imresize.py
ColorTransferLib/Algorithms/Afifi21_2/third_party/utils/pyramid_upsampling.py
ColorTransferLib/Algorithms/Afifi21_2/third_party/utils/vggloss.py
ColorTransferLib/Algorithms/Cao20/Cao20.py
ColorTransferLib/Algorithms/Cao20/__init__.py
colortransferlib-2.1.0.post1.dist-info/licenses/LICENSE
colortransferlib-2.1.0.post1.dist-info/METADATA
colortransferlib-2.1.0.post1.dist-info/WHEEL
colortransferlib-2.1.0.post1.dist-info/top_level.txt
colortransferlib-2.1.0.post1.dist-info/RECORD
