Metadata-Version: 2.4
Name: ColorTransferLib
Version: 2.1.0.post1
Summary: This library provides color and tyle transfer algorithms which were published in scientific papers. Additionall a set of IQA metrics are available.
Author: Herbert Potechius
Author-email: potechius.herbert@gmail.com
Classifier: Programming Language :: Python :: 3
Classifier: License :: OSI Approved :: MIT License
Classifier: Operating System :: POSIX :: Linux
Requires-Python: >=3.12,<3.13
License-File: LICENSE
Requires-Dist: appdirs==1.4.4
Requires-Dist: cog==0.16.8
Requires-Dist: dlib==20.0.0
Requires-Dist: faiss-cpu==1.13.1
Requires-Dist: linear_attention_transformer==0.19.1
Requires-Dist: lpips==0.1.4
Requires-Dist: networkx==3.6.1
Requires-Dist: open3d==0.19.0
Requires-Dist: opencv-contrib-python==4.12.0.88
Requires-Dist: phasepack==1.5
Requires-Dist: plyfile==1.1.3
Requires-Dist: pyamg==5.3.0
Requires-Dist: pyfftw==0.15.1
Requires-Dist: pyhull==2015.2.1
Requires-Dist: pyiqa==0.1.14.1
Requires-Dist: pyntcloud==0.3.1
Requires-Dist: retry==0.9.2
Requires-Dist: scikit-fuzzy==0.5.0
Requires-Dist: scikit-image==0.25.2
Requires-Dist: tensorflow==2.20.0
Requires-Dist: tf_slim==1.1.0
Requires-Dist: timm==1.0.22
Requires-Dist: torch==2.9.1
Requires-Dist: torch_optimizer==0.3.0
Requires-Dist: torchmetrics==1.8.2
Requires-Dist: torchvision==0.24.1
Requires-Dist: vector_quantize_pytorch==1.27.12
Dynamic: author
Dynamic: author-email
Dynamic: classifier
Dynamic: description
Dynamic: description-content-type
Dynamic: license-file
Dynamic: requires-dist
Dynamic: requires-python
Dynamic: summary
